{
    "DNDConfig": null,
    "__parentReadjusting__": false,
    "_height_": {
        "type": "string",
        "value": "100%"
    },
    "_left_": {
        "type": "string",
        "value": "0dp"
    },
    "_margin_": [
        0,
        0,
        0,
        0
    ],
    "_orientation_": 6,
    "_padding_": [
        0,
        0,
        0,
        0
    ],
    "_percent_": true,
    "_skin_": "sd62dd34ac3e481b87487ab023a0e579",
    "_top_": {
        "type": "string",
        "value": "0dp"
    },
    "_width_": {
        "type": "string",
        "value": "100%"
    },
    "allboxes": [],
    "autogrowmode": 0,
    "canUpdateUI": true,
    "children": [
        "MapNear",
        "FlxHeader",
        "FlexContainer0e62f594b7bbc4a",
        "FlexContainer0fdbce89d215b4c"
    ],
    "clipbounds": true,
    "containerweight": 100,
    "enablescrolling": true,
    "id": "FlxContainer",
    "info": null,
    "iscustomlayout": false,
    "isvisible": true,
    "kuid": "gc5491baaa96497f99832d86132c2f11",
    "layouttype": 2,
    "name": "kony.ui.FlexContainer",
    "parent": "WhatNearMe",
    "pf": "WhatNearMe",
    "retaincontentalignment": false,
    "retainflexpositionproperties": false,
    "snapgridsize": 10,
    "snaptogrid": true,
    "wType": "FlexContainer",
    "widgetalignment": 1,
    "zindex": 1
}