{
    "DNDConfig": null,
    "__parentReadjusting__": false,
    "_height_": {
        "type": "string",
        "value": "22dp"
    },
    "_left_": {
        "type": "string",
        "value": "105dp"
    },
    "_margin_": [
        0,
        0,
        0,
        0
    ],
    "_orientation_": 6,
    "_padding_": [
        0,
        0,
        0,
        0
    ],
    "_percent_": true,
    "_right_": {
        "type": "string",
        "value": "1dp"
    },
    "_skin_": "sd62dd34ac3e481b87487ab023a0e579",
    "_top_": {
        "type": "string",
        "value": "0dp"
    },
    "allboxes": [],
    "autogrowmode": 0,
    "canUpdateUI": true,
    "children": [
        "lblPhone1",
        "lblPhoneNumberSeparator",
        "lblPhone2"
    ],
    "clipbounds": true,
    "containerweight": 100,
    "enablescrolling": true,
    "id": "FlexContainer0e1a119faf64a49",
    "ide_onClick": "AS_FlexContainer_dceb2587a0c349d5b8af4b406aaf179b",
    "info": null,
    "iscustomlayout": false,
    "isvisible": true,
    "kuid": "fc511912915b43c5b44d1f7fbeaa768e",
    "layouttype": 3,
    "name": "kony.ui.FlexContainer",
    "parent": "CopyFlexContainer0h191f495005643",
    "pf": "FrmDirectoryDescription",
    "retaincontentalignment": false,
    "retainflexpositionproperties": false,
    "snapgridsize": 10,
    "snaptogrid": true,
    "wType": "FlexContainer",
    "widgetalignment": 1,
    "zindex": 1
}