{
    "@class": "com.kony.gen.viz.model.component.KVizLabel",
    "DNDConfig": null,
    "__parentReadjusting__": false,
    "_height_": {
        "type": "ref",
        "value": "preferred"
    },
    "_margin_": [
        1,
        1,
        1,
        1
    ],
    "_padding_": [
        0,
        0,
        0,
        0
    ],
    "_skin_": "s61cee5ea7ec4f91ac2f68b5e8934d08",
    "_text_": "Swipe down from the header to access main menu.",
    "_top_": {
        "type": "string",
        "value": "4%"
    },
    "_width_": {
        "type": "string",
        "value": "75%"
    },
    "_wrapping_": 2,
    "android": {
        "textStyle": {
            "letterSpacing": 0,
            "strikeThrough": false
        }
    },
    "canUpdateUI": true,
    "centerx": {
        "type": "string",
        "value": "50%"
    },
    "containerweight": 100,
    "contentalignment": 5,
    "id": "lblTextSwipeTuto00",
    "info": null,
    "ipad": {
        "psp": {
            "wrapping": 2
        }
    },
    "iphone": {
        "psp": {
            "wrapping": 2
        }
    },
    "iscustomlayout": false,
    "isvisible": true,
    "kuid": "d9c40948f234453bad8410a3ce40335e",
    "name": "kony.ui.Label",
    "parent": "flxBGDistortedTutorial",
    "pf": "frmTutorial",
    "retaincontentalignment": false,
    "retainflexpositionproperties": false,
    "textstyle": {},
    "tooltip": "",
    "wType": "Label",
    "zindex": 1
}